odoo/addons/edi_sale_endpoint/README.rst
odoo/addons/edi_sale_endpoint/__init__.py
odoo/addons/edi_sale_endpoint/__manifest__.py
odoo/addons/edi_sale_endpoint/i18n/edi_sale_endpoint.pot
odoo/addons/edi_sale_endpoint/i18n/it.po
odoo/addons/edi_sale_endpoint/readme/CONTRIBUTORS.rst
odoo/addons/edi_sale_endpoint/readme/DESCRIPTION.rst
odoo/addons/edi_sale_endpoint/static/description/icon.png
odoo/addons/edi_sale_endpoint/static/description/index.html
odoo/addons/edi_sale_endpoint/views/sale_order.xml
odoo14_addon_edi_sale_endpoint-14.0.1.0.1.dev4.dist-info/METADATA
odoo14_addon_edi_sale_endpoint-14.0.1.0.1.dev4.dist-info/WHEEL
odoo14_addon_edi_sale_endpoint-14.0.1.0.1.dev4.dist-info/top_level.txt
odoo14_addon_edi_sale_endpoint-14.0.1.0.1.dev4.dist-info/RECORD
