Metadata-Version: 2.1
Name: odoo14-addon-edi_sale_endpoint
Version: 14.0.1.0.1.dev4
Summary: Glue module between edi_sale_oca and edi_endpoint_oca.
Home-page: https://github.com/OCA/edi
Author: Camptocamp,Odoo Community Association (OCA)
Author-email: support@odoo-community.org
License: AGPL-3
Classifier: Programming Language :: Python
Classifier: Framework :: Odoo
Classifier: Framework :: Odoo :: 14.0
Classifier: License :: OSI Approved :: GNU Affero General Public License v3
Classifier: Development Status :: 3 - Alpha
Requires-Python: >=3.6
Requires-Dist: odoo14-addon-edi-endpoint-oca
Requires-Dist: odoo14-addon-edi-sale-oca
Requires-Dist: odoo<14.1dev,>=14.0a
